indobert_embedding.py
indobert_embedding-0.0.1.dist-info/LICENSE
indobert_embedding-0.0.1.dist-info/METADATA
indobert_embedding-0.0.1.dist-info/WHEEL
indobert_embedding-0.0.1.dist-info/top_level.txt
indobert_embedding-0.0.1.dist-info/RECORD
