Metadata-Version: 2.1
Name: indobert-embedding
Version: 0.0.1
Summary: Text embedding encoder using IndoBERT
Author: Robin Syihab
License: MIT
Classifier: Programming Language :: Python :: 3
Classifier: License :: OSI Approved :: MIT License
Classifier: Operating System :: OS Independent
Requires-Python: >=3.6
License-File: LICENSE
Requires-Dist: transformers ==4.33.2
Requires-Dist: accelerate ==0.20.3
Requires-Dist: numpy ==1.24.2
Requires-Dist: torch ==2.0.0
Requires-Dist: torchmetrics ==0.11.4
